setup.py
webpigpio/__init__.py
webpigpio/gpio.py
webpigpio.egg-info/PKG-INFO
webpigpio.egg-info/SOURCES.txt
webpigpio.egg-info/dependency_links.txt
webpigpio.egg-info/top_level.txt