Metadata-Version: 1.0
Name: webpigpio
Version: 0.1.0
Summary: Command GPIO via options bag, used for a web driven gpio contoller for raspberry pi
Home-page: https://github.com/sachinio/pilibs/tree/master/src/webpigpio
Author: Sachin Patney
Author-email: UNKNOWN
License: MIT
Platform: UNKNOWN
